twinotter/__init__.py
twinotter/derive.py
twinotter/quicklook.py
twinotter/summary.py
twinotter/data/__init__.py
twinotter/data/ccn.py
twinotter/external/__init__.py
twinotter/external/eurec4a/__init__.py
twinotter/external/goes/__init__.py
twinotter/external/goes/download_matching.py
twinotter/external/goes/plot.py
twinotter/plots/__init__.py
twinotter/plots/basic_flight_track.py
twinotter/plots/flight_track_frames.py
twinotter/plots/heights_and_legs.py
twinotter/plots/interactive_flight_track.py
twinotter/plots/vertical_profile.py
twinotter/util/__init__.py
twinotter/util/scripting.py
twinotter-0.3.0.dist-info/LICENSE
twinotter-0.3.0.dist-info/METADATA
twinotter-0.3.0.dist-info/WHEEL
twinotter-0.3.0.dist-info/top_level.txt
twinotter-0.3.0.dist-info/RECORD
