Metadata-Version: 2.1
Name: twinotter
Version: 0.3.0
Summary: Software for working with data from the BAS twin otter
Home-page: UNKNOWN
Author: eurec4a
Author-email: UNKNOWN
License: MIT license
Platform: UNKNOWN
Classifier: Development Status :: 2 - Pre-Alpha
Classifier: License :: OSI Approved :: MIT License
Classifier: Natural Language :: English
Classifier: Programming Language :: Python
Classifier: Programming Language :: Python :: 3
Classifier: Topic :: Scientific/Engineering :: Atmospheric Science
Requires-Dist: xarray
Requires-Dist: numpy
Requires-Dist: matplotlib
Requires-Dist: pandas
Requires-Dist: metpy (>=1.0)
Requires-Dist: cartopy
Requires-Dist: parse
Requires-Dist: tqdm
Requires-Dist: cftime
Requires-Dist: worldview-dl
Requires-Dist: docopt
Requires-Dist: netcdf4
Requires-Dist: pyyaml
